smart_commit/__init__.py
smart_commit/cli.py
smart_commit/git_commit_generator.py
smart_commit/models.py
smart_commit/prompts.py
smart_commit/py.typed
smart_commit/settings.py
lazy_commit-0.1.4.dist-info/METADATA
lazy_commit-0.1.4.dist-info/WHEEL
lazy_commit-0.1.4.dist-info/entry_points.txt
lazy_commit-0.1.4.dist-info/licenses/LICENSE
lazy_commit-0.1.4.dist-info/RECORD
