Metadata-Version: 2.4
Name: lazy-commit
Version: 0.1.4
Summary: A git commit message generator for personal use.
Author-email: QIN2DIM <yaoqinse@gmail.com>
License-File: LICENSE
Requires-Python: >=3.12
Requires-Dist: loguru>=0.7.3
Requires-Dist: openai>=1.97.0
Requires-Dist: pydantic-settings>=2.10.1
Requires-Dist: rich>=13.0.0
Requires-Dist: tiktoken>=0.9.0
Requires-Dist: typer>=0.16.0
